{
"meta":{"test_sets":[],"test_metrics":[],"learn_metrics":[{"best_value":"Min","name":"RMSE"}],"launch_mode":"Train","parameters":"","iteration_count":100,"learn_sets":["learn"],"name":"experiment"},
"iterations":[
{"learn":[14.005006],"iteration":0,"passed_time":0.001256136602,"remaining_time":0.1243575236},
{"learn":[13.14441192],"iteration":1,"passed_time":0.002282168627,"remaining_time":0.1118262627},
{"learn":[12.34258257],"iteration":2,"passed_time":0.003209754831,"remaining_time":0.1037820729},
{"learn":[11.64527793],"iteration":3,"passed_time":0.003956148594,"remaining_time":0.09494756625},
{"learn":[11.02766183],"iteration":4,"passed_time":0.004898040519,"remaining_time":0.09306276987},
{"learn":[10.43485794],"iteration":5,"passed_time":0.005812022754,"remaining_time":0.09105502314},
{"learn":[9.890641275],"iteration":6,"passed_time":0.00675114777,"remaining_time":0.08969382038},
{"learn":[9.492161212],"iteration":7,"passed_time":0.00768956101,"remaining_time":0.08842995161},
{"learn":[9.105082953],"iteration":8,"passed_time":0.008682901403,"remaining_time":0.08779378086},
{"learn":[8.674157135],"iteration":9,"passed_time":0.009603790886,"remaining_time":0.08643411797},
{"learn":[8.341743544],"iteration":10,"passed_time":0.01051531699,"remaining_time":0.0850784738},
{"learn":[8.049372916],"iteration":11,"passed_time":0.01146200088,"remaining_time":0.08405467311},
{"learn":[7.757318612],"iteration":12,"passed_time":0.01236806334,"remaining_time":0.08277088541},
{"learn":[7.522206899],"iteration":13,"passed_time":0.01329575982,"remaining_time":0.08167395316},
{"learn":[7.297756655],"iteration":14,"passed_time":0.01442908977,"remaining_time":0.08176484201},
{"learn":[7.088359431],"iteration":15,"passed_time":0.01536069601,"remaining_time":0.08064365405},
{"learn":[6.882113791],"iteration":16,"passed_time":0.01629000652,"remaining_time":0.07953356124},
{"learn":[6.704728832],"iteration":17,"passed_time":0.01720207397,"remaining_time":0.07836500365},
{"learn":[6.563881962],"iteration":18,"passed_time":0.01810067781,"remaining_time":0.07716604749},
{"learn":[6.418790279],"iteration":19,"passed_time":0.01902519635,"remaining_time":0.0761007854},
{"learn":[6.315756953],"iteration":20,"passed_time":0.01993305329,"remaining_time":0.07498624809},
{"learn":[6.210157751],"iteration":21,"passed_time":0.02086533121,"remaining_time":0.07397708338},
{"learn":[6.115058449],"iteration":22,"passed_time":0.02176913804,"remaining_time":0.07287928821},
{"learn":[6.014819884],"iteration":23,"passed_time":0.0229520919,"remaining_time":0.07268162435},
{"learn":[5.93117229],"iteration":24,"passed_time":0.02395672048,"remaining_time":0.07187016144},
{"learn":[5.844857622],"iteration":25,"passed_time":0.02491097327,"remaining_time":0.07090046238},
{"learn":[5.771145213],"iteration":26,"passed_time":0.0258556321,"remaining_time":0.06990596828},
{"learn":[5.704018229],"iteration":27,"passed_time":0.02676600533,"remaining_time":0.06882687084},
{"learn":[5.665806474],"iteration":28,"passed_time":0.02771378195,"remaining_time":0.06785098339},
{"learn":[5.616500369],"iteration":29,"passed_time":0.02862084691,"remaining_time":0.06678197612},
{"learn":[5.558023666],"iteration":30,"passed_time":0.02958663851,"remaining_time":0.06585413088},
{"learn":[5.510080976],"iteration":31,"passed_time":0.03048164336,"remaining_time":0.06477349214},
{"learn":[5.468747792],"iteration":32,"passed_time":0.03139619702,"remaining_time":0.06374379395},
{"learn":[5.429275534],"iteration":33,"passed_time":0.03233643482,"remaining_time":0.06277072641},
{"learn":[5.402117324],"iteration":34,"passed_time":0.03324371031,"remaining_time":0.06173831914},
{"learn":[5.367635151],"iteration":35,"passed_time":0.03414824896,"remaining_time":0.06070799815},
{"learn":[5.345181232],"iteration":36,"passed_time":0.03506973994,"remaining_time":0.05971334098},
{"learn":[5.319151269],"iteration":37,"passed_time":0.03620393205,"remaining_time":0.05906957334},
{"learn":[5.296134146],"iteration":38,"passed_time":0.03727039503,"remaining_time":0.05829472043},
{"learn":[5.269629003],"iteration":39,"passed_time":0.0382094198,"remaining_time":0.05731412969},
{"learn":[5.251147059],"iteration":40,"passed_time":0.03915636434,"remaining_time":0.05634696331},
{"learn":[5.248003302],"iteration":41,"passed_time":0.03958506481,"remaining_time":0.0546650895},
{"learn":[5.232376509],"iteration":42,"passed_time":0.04049194932,"remaining_time":0.05367537469},
{"learn":[5.213524255],"iteration":43,"passed_time":0.04142304429,"remaining_time":0.05272023819},
{"learn":[5.189691584],"iteration":44,"passed_time":0.04233849018,"remaining_time":0.05174704355},
{"learn":[5.166052198],"iteration":45,"passed_time":0.0432863871,"remaining_time":0.05081445442},
{"learn":[5.140406659],"iteration":46,"passed_time":0.04426294559,"remaining_time":0.04991353439},
{"learn":[5.118929684],"iteration":47,"passed_time":0.04518558945,"remaining_time":0.04895105524},
{"learn":[5.108792602],"iteration":48,"passed_time":0.04608394266,"remaining_time":0.04796491991},
{"learn":[5.098141225],"iteration":49,"passed_time":0.0470013735,"remaining_time":0.0470013735},
{"learn":[5.085926393],"iteration":50,"passed_time":0.04792491962,"remaining_time":0.04604551101},
{"learn":[5.067816804],"iteration":51,"passed_time":0.04883553344,"remaining_time":0.04507895395},
{"learn":[5.049834901],"iteration":52,"passed_time":0.04975514975,"remaining_time":0.04412249129},
{"learn":[5.03838627],"iteration":53,"passed_time":0.0508660136,"remaining_time":0.04333030788},
{"learn":[5.033534248],"iteration":54,"passed_time":0.05148885886,"remaining_time":0.04212724816},
{"learn":[5.023726885],"iteration":55,"passed_time":0.05239930226,"remaining_time":0.04117088034},
{"learn":[5.01290392],"iteration":56,"passed_time":0.05332120427,"remaining_time":0.04022476813},
{"learn":[5.005569127],"iteration":57,"passed_time":0.05426189319,"remaining_time":0.03929309507},
{"learn":[4.989969032],"iteration":58,"passed_time":0.05517040176,"remaining_time":0.03833875376},
{"learn":[4.976762446],"iteration":59,"passed_time":0.05608387271,"remaining_time":0.03738924848},
{"learn":[4.967222715],"iteration":60,"passed_time":0.05698679734,"remaining_time":0.0364341819},
{"learn":[4.954407599],"iteration":61,"passed_time":0.05790974195,"remaining_time":0.03549306765},
{"learn":[4.942125056],"iteration":62,"passed_time":0.05889054103,"remaining_time":0.03458650822},
{"learn":[4.930230716],"iteration":63,"passed_time":0.05983324498,"remaining_time":0.0336562003},
{"learn":[4.921695642],"iteration":64,"passed_time":0.06077126724,"remaining_time":0.03272299005},
{"learn":[4.906405625],"iteration":65,"passed_time":0.0617065627,"remaining_time":0.03178822927},
{"learn":[4.894330248],"iteration":66,"passed_time":0.06261547227,"remaining_time":0.03084045649},
{"learn":[4.88211557],"iteration":67,"passed_time":0.06351290317,"remaining_time":0.02988842502},
{"learn":[4.877946398],"iteration":68,"passed_time":0.06465170679,"remaining_time":0.02904641899},
{"learn":[4.863182126],"iteration":69,"passed_time":0.06560650093,"remaining_time":0.02811707183},
{"learn":[4.84646533],"iteration":70,"passed_time":0.0665524931,"remaining_time":0.02718341267},
{"learn":[4.838014752],"iteration":71,"passed_time":0.06746795904,"remaining_time":0.02623753963},
{"learn":[4.82981137],"iteration":72,"passed_time":0.06839339988,"remaining_time":0.025296189},
{"learn":[4.817094767],"iteration":73,"passed_time":0.06931695602,"remaining_time":0.02435460617},
{"learn":[4.808314151],"iteration":74,"passed_time":0.07022518389,"remaining_time":0.02340839463},
{"learn":[4.796235023],"iteration":75,"passed_time":0.07115022374,"remaining_time":0.02246849171},
{"learn":[4.784434534],"iteration":76,"passed_time":0.07204660201,"remaining_time":0.02152041359},
{"learn":[4.774402487],"iteration":77,"passed_time":0.07296584739,"remaining_time":0.0205801108},
{"learn":[4.76731896],"iteration":78,"passed_time":0.07394100237,"remaining_time":0.01965520316},
{"learn":[4.75934113],"iteration":79,"passed_time":0.07487199709,"remaining_time":0.01871799927},
{"learn":[4.754106378],"iteration":80,"passed_time":0.07576804454,"remaining_time":0.01777275119},
{"learn":[4.744002932],"iteration":81,"passed_time":0.07668440271,"remaining_time":0.01683316157},
{"learn":[4.731700554],"iteration":82,"passed_time":0.0775790266,"remaining_time":0.01588968015},
{"learn":[4.723284153],"iteration":83,"passed_time":0.07860019649,"remaining_time":0.014971466},
{"learn":[4.712232782],"iteration":84,"passed_time":0.07953315611,"remaining_time":0.01403526284},
{"learn":[4.703046867],"iteration":85,"passed_time":0.08045805561,"remaining_time":0.01309782301},
{"learn":[4.698601855],"iteration":86,"passed_time":0.08135853412,"remaining_time":0.01215702234},
{"learn":[4.692429407],"iteration":87,"passed_time":0.08226223067,"remaining_time":0.01121757691},
{"learn":[4.675027364],"iteration":88,"passed_time":0.08317100991,"remaining_time":0.01027956302},
{"learn":[4.662368584],"iteration":89,"passed_time":0.08409070642,"remaining_time":0.009343411824},
{"learn":[4.646206172],"iteration":90,"passed_time":0.08498588169,"remaining_time":0.00840519709},
{"learn":[4.641245848],"iteration":91,"passed_time":0.08589878122,"remaining_time":0.007469459237},
{"learn":[4.633900435],"iteration":92,"passed_time":0.0868337258,"remaining_time":0.006535871834},
{"learn":[4.624738236],"iteration":93,"passed_time":0.08775142732,"remaining_time":0.005601154935},
{"learn":[4.612798287],"iteration":94,"passed_time":0.08873408103,"remaining_time":0.004670214791},
{"learn":[4.605222001],"iteration":95,"passed_time":0.08964593796,"remaining_time":0.003735247415},
{"learn":[4.601725912],"iteration":96,"passed_time":0.09054921346,"remaining_time":0.002800491138},
{"learn":[4.59722371],"iteration":97,"passed_time":0.09144798772,"remaining_time":0.001866285464},
{"learn":[4.580235665],"iteration":98,"passed_time":0.09287638446,"remaining_time":0.0009381452975},
{"learn":[4.57591791],"iteration":99,"passed_time":0.09416848085,"remaining_time":0}
]}